pystext/__init__.py
pystext/_version.py
pystext/py.typed
pystext-0.0.1a1.dist-info/METADATA
pystext-0.0.1a1.dist-info/WHEEL
pystext-0.0.1a1.dist-info/RECORD
